pan_mcp_relay/__init__.py
pan_mcp_relay/configuration.py
pan_mcp_relay/constants.py
pan_mcp_relay/exceptions.py
pan_mcp_relay/main.py
pan_mcp_relay/pan_security_relay.py
pan_mcp_relay/security_scanner.py
pan_mcp_relay/tool.py
pan_mcp_relay/tool_registry.py
pan_mcp_relay/utils.py
pan_mcp_relay/client/__init__.py
pan_mcp_relay/client/client.py
pan_mcp_relay/client/session_group.py
pan_mcp_relay/server/__init__.py
pan_mcp_relay/server/server.py
pan_mcp_relay/_version.py
pan_mcp_relay-0.0.5b1.dist-info/METADATA
pan_mcp_relay-0.0.5b1.dist-info/WHEEL
pan_mcp_relay-0.0.5b1.dist-info/entry_points.txt
pan_mcp_relay-0.0.5b1.dist-info/licenses/LICENSE
pan_mcp_relay-0.0.5b1.dist-info/RECORD
