Metadata-Version: 2.4
Name: pan-mcp-relay
Version: 0.0.5b1
Summary: Palo Alto Networks AI Security MCP Relay
Project-URL: Homepage, https://www.paloaltonetworks.com/prisma/prisma-ai-runtime-security
Project-URL: Documentation, https://pan.dev/prisma-airs/scan/api/
Project-URL: Docs, https://docs.paloaltonetworks.com/ai-runtime-security
Project-URL: Repository, https://github.com/paloaltonetworks/aisecurity-mcp-relay.git
Project-URL: Issues, https://github.com/paloaltonetworks/aisecurity-mcp-relay/issues
License-File: LICENSE
Keywords: AI Runtime Security,AI Security,MCP Relay,MCP Security,Model Context Protocol,Palo Alto Networks,PaloAltoNetworks,Prompt Injection
Requires-Python: >=3.12
Requires-Dist: anyio>=4.10.0
Requires-Dist: backports-strenum<2.0,>=1.3.1; python_full_version < '3.11'
Requires-Dist: click>=8.2.1
Requires-Dist: httpx[http2]>=0.28.1
Requires-Dist: mcp[cli,rich,ws]>=1.12.1
Requires-Dist: pan-aisecurity>=0.4.0.5.post2
Requires-Dist: pydantic-settings[yaml]>=2.10.1
Requires-Dist: pydantic>=2.11.7
Requires-Dist: python-dotenv>=1.1.1
Requires-Dist: rich>=14.0
Requires-Dist: tenacity>=9.1.2
Requires-Dist: truststore>=0.10.4
